overcomplete/__init__.py
overcomplete/base.py
overcomplete/data.py
overcomplete/metrics.py
overcomplete/models.py
overcomplete/optimization/__init__.py
overcomplete/optimization/archetypal_analysis.py
overcomplete/optimization/base.py
overcomplete/optimization/convex_nmf.py
overcomplete/optimization/nmf.py
overcomplete/optimization/semi_nmf.py
overcomplete/optimization/sklearn_wrappers.py
overcomplete/optimization/utils.py
overcomplete/sae/__init__.py
overcomplete/sae/archetypal_dictionary.py
overcomplete/sae/base.py
overcomplete/sae/batchtopk_sae.py
overcomplete/sae/dictionary.py
overcomplete/sae/factory.py
overcomplete/sae/jump_sae.py
overcomplete/sae/kernels.py
overcomplete/sae/losses.py
overcomplete/sae/modules.py
overcomplete/sae/mp_sae.py
overcomplete/sae/omp_sae.py
overcomplete/sae/optimizer.py
overcomplete/sae/qsae.py
overcomplete/sae/rasae.py
overcomplete/sae/topk_sae.py
overcomplete/sae/trackers.py
overcomplete/sae/train.py
overcomplete/visualization/__init__.py
overcomplete/visualization/cmaps.py
overcomplete/visualization/plot_utils.py
overcomplete/visualization/top_concepts.py
overcomplete-0.3.0.dist-info/METADATA
overcomplete-0.3.0.dist-info/WHEEL
overcomplete-0.3.0.dist-info/licenses/LICENSE
overcomplete-0.3.0.dist-info/RECORD
