Metadata-Version: 2.4
Name: Overcomplete
Version: 0.3.0
Summary: Toolbox for experimenting with (Overcomplete) Dictionary Learning for Vision model
License: MIT
License-File: LICENSE
Author: Thomas Fel
Author-email: tfel@g.harvard.edu
Requires-Python: >=3.8,<3.13
Classifier: License :: OSI Approved :: MIT License
Classifier: Programming Language :: Python :: 3
Classifier: Programming Language :: Python :: 3.8
Classifier: Programming Language :: Python :: 3.9
Classifier: Programming Language :: Python :: 3.10
Classifier: Programming Language :: Python :: 3.11
Classifier: Programming Language :: Python :: 3.12
Requires-Dist: einops
Requires-Dist: matplotlib
Requires-Dist: numpy
Requires-Dist: opencv-python
Requires-Dist: scikit-image
Requires-Dist: scikit-learn (>=1.2.0,<2.0.0)
Requires-Dist: scipy
Requires-Dist: timm
Requires-Dist: torch
Requires-Dist: torchvision
